aioca/__init__.py
aioca/__main__.py
aioca/_catools.py
aioca/_version.py
aioca/types.py
aioca-1.8.1.dist-info/LICENSE
aioca-1.8.1.dist-info/METADATA
aioca-1.8.1.dist-info/WHEEL
aioca-1.8.1.dist-info/entry_points.txt
aioca-1.8.1.dist-info/top_level.txt
aioca-1.8.1.dist-info/RECORD
